qrcodeapi/__init__.py
qrcodeapi/api.py
qrcodeapi-0.0.1.dist-info/LICENSE
qrcodeapi-0.0.1.dist-info/METADATA
qrcodeapi-0.0.1.dist-info/WHEEL
qrcodeapi-0.0.1.dist-info/top_level.txt
qrcodeapi-0.0.1.dist-info/RECORD
