Metadata-Version: 2.1
Name: qrcodeapi
Version: 0.0.1
Summary: A Python library for interacting with a QR code generation API (https://qrcode.ness.su)
Home-page: https://github.com/nessshon/qrcode-fastapi/tree/main/pypi
Author: nessshon
Classifier: Programming Language :: Python :: 3.7
Classifier: Programming Language :: Python :: 3.8
Classifier: Programming Language :: Python :: 3.9
Classifier: Programming Language :: Python :: 3.10
Classifier: License :: OSI Approved :: MIT License
Classifier: Operating System :: OS Independent
Requires-Python: >=3.7, <3.12
License-File: LICENSE
Requires-Dist: aiohttp >=3.8.5
